climb_onyx_ui/__init__.py
climb_onyx_ui/_version.py
climb_onyx_ui/handlers.py
climb_onyx_ui-0.6.1.data/data/etc/jupyter/jupyter_server_config.d/climb_onyx_ui.json
climb_onyx_ui-0.6.1.data/data/share/jupyter/labextensions/climb_onyx_ui/build_log.json
climb_onyx_ui-0.6.1.data/data/share/jupyter/labextensions/climb_onyx_ui/package.json
climb_onyx_ui-0.6.1.data/data/share/jupyter/labextensions/climb_onyx_ui/static/lib_index_js.9c5341e2a8b5851e655d.js
climb_onyx_ui-0.6.1.data/data/share/jupyter/labextensions/climb_onyx_ui/static/lib_index_js.9c5341e2a8b5851e655d.js.map
climb_onyx_ui-0.6.1.data/data/share/jupyter/labextensions/climb_onyx_ui/static/remoteEntry.4aa81766691b23d97839.js
climb_onyx_ui-0.6.1.data/data/share/jupyter/labextensions/climb_onyx_ui/static/remoteEntry.4aa81766691b23d97839.js.map
climb_onyx_ui-0.6.1.data/data/share/jupyter/labextensions/climb_onyx_ui/static/style.js
climb_onyx_ui-0.6.1.data/data/share/jupyter/labextensions/climb_onyx_ui/static/style_index_js-data_image_svg_xml_3csvg_xmlns_27http_www_w3_org_2000_svg_27_viewBox_27-4_-4_8-92e3d9.dd5745bc1ff01963a116.js
climb_onyx_ui-0.6.1.data/data/share/jupyter/labextensions/climb_onyx_ui/static/style_index_js-data_image_svg_xml_3csvg_xmlns_27http_www_w3_org_2000_svg_27_viewBox_27-4_-4_8-92e3d9.dd5745bc1ff01963a116.js.map
climb_onyx_ui-0.6.1.data/data/share/jupyter/labextensions/climb_onyx_ui/static/vendors-node_modules_climb-onyx-gui_dist_climb-onyx-gui_js.95e7721f3744b0bc75ac.js
climb_onyx_ui-0.6.1.data/data/share/jupyter/labextensions/climb_onyx_ui/static/vendors-node_modules_climb-onyx-gui_dist_climb-onyx-gui_js.95e7721f3744b0bc75ac.js.map
climb_onyx_ui-0.6.1.data/data/share/jupyter/labextensions/climb_onyx_ui/static/vendors-node_modules_style-loader_dist_runtime_injectStylesIntoStyleTag_js-node_modules_style-9a35e0.e022ac27572ec96893d8.js
climb_onyx_ui-0.6.1.dist-info/METADATA
climb_onyx_ui-0.6.1.dist-info/WHEEL
climb_onyx_ui-0.6.1.dist-info/licenses/LICENSE
climb_onyx_ui-0.6.1.dist-info/RECORD
