Metadata-Version: 2.3
Name: climb_onyx_ui
Version: 0.6.1
Dynamic: Keywords
Summary: A JupyterLab extension adding increased functionality for climb.
Project-URL: Homepage, https://github.com/CLIMB-TRE/onyx-extension
Project-URL: Bug Tracker, https://github.com/CLIMB-TRE/onyx-extension/issues
Project-URL: Repository, https://github.com/CLIMB-TRE/onyx-extension.git
Author: University of Birmingham
License:                     GNU GENERAL PUBLIC LICENSE
License-File: LICENSE
Classifier: Framework :: Jupyter
Classifier: Framework :: Jupyter :: JupyterLab
Classifier: Framework :: Jupyter :: JupyterLab :: 4
Classifier: Framework :: Jupyter :: JupyterLab :: Extensions
Classifier: Framework :: Jupyter :: JupyterLab :: Extensions :: Prebuilt
Classifier: License :: OSI Approved :: BSD License
Classifier: Programming Language :: Python
Classifier: Programming Language :: Python :: 3
Classifier: Programming Language :: Python :: 3.8
Classifier: Programming Language :: Python :: 3.9
Classifier: Programming Language :: Python :: 3.10
Classifier: Programming Language :: Python :: 3.11
Classifier: Programming Language :: Python :: 3.12
Requires-Python: >=3.8
Requires-Dist: boto3
Requires-Dist: jupyter-server<3,>=2.0.1
